Metadata-Version: 2.1
Name: taichi-splatting
Version: 0.13.0
Summary: A Taichi Gaussian Splatting library
Maintainer-email: Oliver Batchelor <oliver.batchelor@canterbury.ac.nz>
License: Apache License
Project-URL: Homepage, https://github.com/uc-vision/taichi-splatting
Requires-Python: >=3.10
License-File: LICENSE
License-File: NOTICE
Requires-Dist: beartype
Requires-Dist: taichi-nightly
Requires-Dist: tqdm
Requires-Dist: tensordict
